CHANGELOG
README.txt
ez_setup.py
setup.py
docs/default.css
docs/index.html
docs/index.rst
docs/logo.gif
docs/mytest-sample.png
scripts/wxFind
scripts/wxoptparse
tests/grepTest.py
tests/manualTest1.py
tests/manualTest2.py
tests/manualTest3.py
tests/mock.py
tests/mytest.py
tests/noDefaultsTest.py
tests/rsync.py
tests/testWxOptParse.py
tests/wxMock.py
wxOptParse.egg-info/PKG-INFO
wxOptParse.egg-info/SOURCES.txt
wxOptParse.egg-info/dependency_links.txt
wxOptParse.egg-info/requires.txt
wxOptParse.egg-info/top_level.txt
wxOptParse.egg-info/zip-safe
wxoptparse/__init__.py
wxoptparse/makeSample.py
